[
    {
        "id": "6450",
        "name": "怪物猎人CFB怪物模型盲包盒蛋 第14弹（随机一款）CAPCOM",
        "englishName": "CFB Monster Hunter Standard Model Plus Vol.14",
        "price": 65,
        "activityPrice": 65,
        "typeOne": 38,
        "typeTwo": 146,
        "themeOne": 45,
        "themeTwo": 239,
        "typeOneName": "模玩",
        "typeTwoName": "不可动手办",
        "themeOneName": "Game",
        "themeTwoName": "Monster Hunter",
        "indexType": "2",
        "buyCount": 27,
        "isSellOut": 2,
        "imageList": "http://datafanthfuloss.oss-cn-shanghai.aliyuncs.com/cpsupload/pic/20190813111400619013.jpg,http://datafanthfuloss.oss-cn-shanghai.aliyuncs.com/cpsupload/pic/20190813111400584133.jpg,http://datafanthfuloss.oss-cn-shanghai.aliyuncs.com/cpsupload/pic/20190813111400516587.jpg,http://datafanthfuloss.oss-cn-shanghai.aliyuncs.com/cpsupload/pic/20190813111400725669.jpg,http://datafanthfuloss.oss-cn-shanghai.aliyuncs.com/cpsupload/pic/20190813111400539975.jpg,http://datafanthfuloss.oss-cn-shanghai.aliyuncs.com/cpsupload/pic/20190813111400479409.jpg,http://datafanthfuloss.oss-cn-shanghai.aliyuncs.com/cpsupload/pic/20190813111400454964.jpg",
        "isExtension": 2,
        "imageStrList": [
            "http://datafanthfuloss.oss-cn-shanghai.aliyuncs.com/cpsupload/pic/20190813111400619013.jpg",
            "http://datafanthfuloss.oss-cn-shanghai.aliyuncs.com/cpsupload/pic/20190813111400584133.jpg",
            "http://datafanthfuloss.oss-cn-shanghai.aliyuncs.com/cpsupload/pic/20190813111400516587.jpg",
            "http://datafanthfuloss.oss-cn-shanghai.aliyuncs.com/cpsupload/pic/20190813111400725669.jpg",
            "http://datafanthfuloss.oss-cn-shanghai.aliyuncs.com/cpsupload/pic/20190813111400539975.jpg",
            "http://datafanthfuloss.oss-cn-shanghai.aliyuncs.com/cpsupload/pic/20190813111400479409.jpg",
            "http://datafanthfuloss.oss-cn-shanghai.aliyuncs.com/cpsupload/pic/20190813111400454964.jpg"
        ]
    },
    {
        "id": "6449",
        "name": "怪物猎人CFB怪物模型盲包盒蛋 第14弹(6个装)CAPCOM",
        "englishName": "CFB Monster Hunter Standard Model Plus Vol.14",
        "price": 360,
        "activityPrice": 360,
        "typeOne": 38,
        "typeTwo": 146,
        "themeOne": 45,
        "themeTwo": 239,
        "typeOneName": "模玩",
        "typeTwoName": "不可动手办",
        "themeOneName": "Game",
        "themeTwoName": "Monster Hunter",
        "indexType": "2",
        "buyCount": 15,
        "isSellOut": 2,
        "imageList": "http://datafanthfuloss.oss-cn-shanghai.aliyuncs.com/cpsupload/pic/20190813111400619013.jpg,http://datafanthfuloss.oss-cn-shanghai.aliyuncs.com/cpsupload/pic/20190813111400584133.jpg,http://datafanthfuloss.oss-cn-shanghai.aliyuncs.com/cpsupload/pic/20190813111400516587.jpg,http://datafanthfuloss.oss-cn-shanghai.aliyuncs.com/cpsupload/pic/20190813111400725669.jpg,http://datafanthfuloss.oss-cn-shanghai.aliyuncs.com/cpsupload/pic/20190813111400539975.jpg,http://datafanthfuloss.oss-cn-shanghai.aliyuncs.com/cpsupload/pic/20190813111400479409.jpg,http://datafanthfuloss.oss-cn-shanghai.aliyuncs.com/cpsupload/pic/20190813111400454964.jpg",
        "isExtension": 2,
        "imageStrList": [
            "http://datafanthfuloss.oss-cn-shanghai.aliyuncs.com/cpsupload/pic/20190813111400619013.jpg",
            "http://datafanthfuloss.oss-cn-shanghai.aliyuncs.com/cpsupload/pic/20190813111400584133.jpg",
            "http://datafanthfuloss.oss-cn-shanghai.aliyuncs.com/cpsupload/pic/20190813111400516587.jpg",
            "http://datafanthfuloss.oss-cn-shanghai.aliyuncs.com/cpsupload/pic/20190813111400725669.jpg",
            "http://datafanthfuloss.oss-cn-shanghai.aliyuncs.com/cpsupload/pic/20190813111400539975.jpg",
            "http://datafanthfuloss.oss-cn-shanghai.aliyuncs.com/cpsupload/pic/20190813111400479409.jpg",
            "http://datafanthfuloss.oss-cn-shanghai.aliyuncs.com/cpsupload/pic/20190813111400454964.jpg"
        ]
    },
    {
        "id": "6443",
        "name": "怪物猎人 Q版玩偶 德特尔 CAPCOM",
        "englishName": "Monster Hunter Chibi-Plush Tetrou",
        "price": 138,
        "activityPrice": 138,
        "typeOne": 38,
        "typeTwo": 303,
        "themeOne": 45,
        "themeTwo": 239,
        "typeOneName": "模玩",
        "typeTwoName": "毛绒玩具",
        "themeOneName": "Game",
        "themeTwoName": "Monster Hunter",
        "indexType": "0",
        "buyCount": 4,
        "isSellOut": 2,
        "imageList": "http://datafanthfuloss.oss-cn-shanghai.aliyuncs.com/cpsupload/pic/20190808155601811781.jpg,http://datafanthfuloss.oss-cn-shanghai.aliyuncs.com/cpsupload/pic/20190808155602053301.jpg,http://datafanthfuloss.oss-cn-shanghai.aliyuncs.com/cpsupload/pic/20190808155601912915.jpg",
        "isExtension": 2,
        "imageStrList": [
            "http://datafanthfuloss.oss-cn-shanghai.aliyuncs.com/cpsupload/pic/20190808155601811781.jpg",
            "http://datafanthfuloss.oss-cn-shanghai.aliyuncs.com/cpsupload/pic/20190808155602053301.jpg",
            "http://datafanthfuloss.oss-cn-shanghai.aliyuncs.com/cpsupload/pic/20190808155601912915.jpg"
        ]
    },
    {
        "id": "6442",
        "name": "怪物猎人 Q版玩偶 冥灯龙 CAPCOM",
        "englishName": "Monster Hunter Chibi-Plush Xeno'jiiva",
        "price": 138,
        "activityPrice": 138,
        "typeOne": 38,
        "typeTwo": 303,
        "themeOne": 45,
        "themeTwo": 239,
        "typeOneName": "模玩",
        "typeTwoName": "毛绒玩具",
        "themeOneName": "Game",
        "themeTwoName": "Monster Hunter",
        "indexType": "0",
        "buyCount": 0,
        "isSellOut": 2,
        "imageList": "http://datafanthfuloss.oss-cn-shanghai.aliyuncs.com/cpsupload/pic/20190808155601833539.jpg,http://datafanthfuloss.oss-cn-shanghai.aliyuncs.com/cpsupload/pic/20190808155601850741.jpg,http://datafanthfuloss.oss-cn-shanghai.aliyuncs.com/cpsupload/pic/20190808155601825233.jpg",
        "isExtension": 2,
        "imageStrList": [
            "http://datafanthfuloss.oss-cn-shanghai.aliyuncs.com/cpsupload/pic/20190808155601833539.jpg",
            "http://datafanthfuloss.oss-cn-shanghai.aliyuncs.com/cpsupload/pic/20190808155601850741.jpg",
            "http://datafanthfuloss.oss-cn-shanghai.aliyuncs.com/cpsupload/pic/20190808155601825233.jpg"
        ]
    },
    {
        "id": "6415",
        "name": "怪物猎人世界夹克",
        "englishName": "Monster Hunter World Jacket",
        "price": 279,
        "activityPrice": 279,
        "typeOne": 36,
        "typeTwo": 136,
        "themeOne": 45,
        "themeTwo": 239,
        "typeOneName": "服饰",
        "typeTwoName": "外套",
        "themeOneName": "Game",
        "themeTwoName": "Monster Hunter",
        "indexType": "8",
        "buyCount": 5,
        "isSellOut": 2,
        "imageList": "http://datafanthfuloss.oss-cn-shanghai.aliyuncs.com/cpsupload/pic/20190726170902716775.jpg,http://datafanthfuloss.oss-cn-shanghai.aliyuncs.com/cpsupload/pic/20190726170902736000.jpg,http://datafanthfuloss.oss-cn-shanghai.aliyuncs.com/cpsupload/pic/20190726170902789982.jpg,http://datafanthfuloss.oss-cn-shanghai.aliyuncs.com/cpsupload/pic/20190726170902774240.jpg,http://datafanthfuloss.oss-cn-shanghai.aliyuncs.com/cpsupload/pic/20190726170902780745.jpg",
        "isExtension": 2,
        "imageStrList": [
            "http://datafanthfuloss.oss-cn-shanghai.aliyuncs.com/cpsupload/pic/20190726170902716775.jpg",
            "http://datafanthfuloss.oss-cn-shanghai.aliyuncs.com/cpsupload/pic/20190726170902736000.jpg",
            "http://datafanthfuloss.oss-cn-shanghai.aliyuncs.com/cpsupload/pic/20190726170902789982.jpg",
            "http://datafanthfuloss.oss-cn-shanghai.aliyuncs.com/cpsupload/pic/20190726170902774240.jpg",
            "http://datafanthfuloss.oss-cn-shanghai.aliyuncs.com/cpsupload/pic/20190726170902780745.jpg"
        ]
    },
    {
        "id": "6404",
        "name": "怪物猎人 粘土人 猎人♀ 麒麟・Edition（再贩）",
        "englishName": "Nendoroid Hunter: Female - Kirin Edition",
        "price": 376,
        "activityPrice": 376,
        "typeOne": 38,
        "typeTwo": 332,
        "themeOne": 45,
        "themeTwo": 239,
        "typeOneName": "模玩",
        "typeTwoName": "Good Smile",
        "themeOneName": "Game",
        "themeTwoName": "Monster Hunter",
        "buyCount": 0,
        "isSellOut": 2,
        "imageList": "http://datafanthfuloss.oss-cn-shanghai.aliyuncs.com/cpsupload/pic/20190702171201495133.jpg,http://datafanthfuloss.oss-cn-shanghai.aliyuncs.com/cpsupload/pic/20190702171201314547.jpg,http://datafanthfuloss.oss-cn-shanghai.aliyuncs.com/cpsupload/pic/20190702171201383928.jpg,http://datafanthfuloss.oss-cn-shanghai.aliyuncs.com/cpsupload/pic/20190702171201380348.jpg,http://datafanthfuloss.oss-cn-shanghai.aliyuncs.com/cpsupload/pic/20190702171201498470.jpg,http://datafanthfuloss.oss-cn-shanghai.aliyuncs.com/cpsupload/pic/20190702171201473410.jpg",
        "isExtension": 2,
        "imageStrList": [
            "http://datafanthfuloss.oss-cn-shanghai.aliyuncs.com/cpsupload/pic/20190702171201495133.jpg",
            "http://datafanthfuloss.oss-cn-shanghai.aliyuncs.com/cpsupload/pic/20190702171201314547.jpg",
            "http://datafanthfuloss.oss-cn-shanghai.aliyuncs.com/cpsupload/pic/20190702171201383928.jpg",
            "http://datafanthfuloss.oss-cn-shanghai.aliyuncs.com/cpsupload/pic/20190702171201380348.jpg",
            "http://datafanthfuloss.oss-cn-shanghai.aliyuncs.com/cpsupload/pic/20190702171201498470.jpg",
            "http://datafanthfuloss.oss-cn-shanghai.aliyuncs.com/cpsupload/pic/20190702171201473410.jpg"
        ]
    },
    {
        "id": "6403",
        "name": "怪物猎人世界文具套装",
        "englishName": "Monster Hunter World Stationary Set",
        "price": 79,
        "activityPrice": 79,
        "typeOne": 41,
        "typeTwo": 159,
        "themeOne": 45,
        "themeTwo": 239,
        "typeOneName": "文具",
        "typeTwoName": "笔记本",
        "themeOneName": "Game",
        "themeTwoName": "Monster Hunter",
        "indexType": "8",
        "buyCount": 5,
        "isSellOut": 2,
        "imageList": "http://datafanthfuloss.oss-cn-shanghai.aliyuncs.com/cpsupload/pic/20190702163405616410.jpg,http://datafanthfuloss.oss-cn-shanghai.aliyuncs.com/cpsupload/pic/20190702163405698856.jpg,http://datafanthfuloss.oss-cn-shanghai.aliyuncs.com/cpsupload/pic/20190702163405695519.jpg,http://datafanthfuloss.oss-cn-shanghai.aliyuncs.com/cpsupload/pic/20190702163405666239.jpg,http://datafanthfuloss.oss-cn-shanghai.aliyuncs.com/cpsupload/pic/20190702163405654136.jpg,http://datafanthfuloss.oss-cn-shanghai.aliyuncs.com/cpsupload/pic/20190702163405784438.jpg,http://datafanthfuloss.oss-cn-shanghai.aliyuncs.com/cpsupload/pic/20190702163405753855.jpg",
        "isExtension": 2,
        "imageStrList": [
            "http://datafanthfuloss.oss-cn-shanghai.aliyuncs.com/cpsupload/pic/20190702163405616410.jpg",
            "http://datafanthfuloss.oss-cn-shanghai.aliyuncs.com/cpsupload/pic/20190702163405698856.jpg",
            "http://datafanthfuloss.oss-cn-shanghai.aliyuncs.com/cpsupload/pic/20190702163405695519.jpg",
            "http://datafanthfuloss.oss-cn-shanghai.aliyuncs.com/cpsupload/pic/20190702163405666239.jpg",
            "http://datafanthfuloss.oss-cn-shanghai.aliyuncs.com/cpsupload/pic/20190702163405654136.jpg",
            "http://datafanthfuloss.oss-cn-shanghai.aliyuncs.com/cpsupload/pic/20190702163405784438.jpg",
            "http://datafanthfuloss.oss-cn-shanghai.aliyuncs.com/cpsupload/pic/20190702163405753855.jpg"
        ]
    },
    {
        "id": "6401",
        "name": "怪物猎人世界MHW毛绒公仔软弹-柔毛秧鸡 CAPCOM",
        "englishName": "MH Mochi-Kawa-Plush FuwafuwaKuina",
        "price": 88,
        "activityPrice": 88,
        "typeOne": 38,
        "typeTwo": 303,
        "themeOne": 45,
        "themeTwo": 239,
        "typeOneName": "模玩",
        "typeTwoName": "毛绒玩具",
        "themeOneName": "Game",
        "themeTwoName": "Monster Hunter",
        "indexType": "0",
        "buyCount": 2,
        "isSellOut": 2,
        "imageList": "http://datafanthfuloss.oss-cn-shanghai.aliyuncs.com/cpsupload/pic/20190701183603996081.jpg,http://datafanthfuloss.oss-cn-shanghai.aliyuncs.com/cpsupload/pic/20190701183603993865.jpg,http://datafanthfuloss.oss-cn-shanghai.aliyuncs.com/cpsupload/pic/20190701183603979017.jpg,http://datafanthfuloss.oss-cn-shanghai.aliyuncs.com/cpsupload/pic/20190701183603912747.jpg",
        "isExtension": 2,
        "imageStrList": [
            "http://datafanthfuloss.oss-cn-shanghai.aliyuncs.com/cpsupload/pic/20190701183603996081.jpg",
            "http://datafanthfuloss.oss-cn-shanghai.aliyuncs.com/cpsupload/pic/20190701183603993865.jpg",
            "http://datafanthfuloss.oss-cn-shanghai.aliyuncs.com/cpsupload/pic/20190701183603979017.jpg",
            "http://datafanthfuloss.oss-cn-shanghai.aliyuncs.com/cpsupload/pic/20190701183603912747.jpg"
        ]
    },
    {
        "id": "6400",
        "name": "怪物猎人世界MHW毛绒公仔软弹[飞雷龙]玩偶官方正版游戏周边 CAPCOM",
        "englishName": "MH Mochi-Kawa-Plush Tobikagachi",
        "price": 88,
        "activityPrice": 88,
        "typeOne": 38,
        "typeTwo": 303,
        "themeOne": 45,
        "themeTwo": 239,
        "typeOneName": "模玩",
        "typeTwoName": "毛绒玩具",
        "themeOneName": "Game",
        "themeTwoName": "Monster Hunter",
        "indexType": "0",
        "buyCount": 1,
        "isSellOut": 2,
        "imageList": "http://datafanthfuloss.oss-cn-shanghai.aliyuncs.com/cpsupload/pic/20190628142502025234.jpg,http://datafanthfuloss.oss-cn-shanghai.aliyuncs.com/cpsupload/pic/20190628142502016174.jpg",
        "isExtension": 2,
        "imageStrList": [
            "http://datafanthfuloss.oss-cn-shanghai.aliyuncs.com/cpsupload/pic/20190628142502025234.jpg",
            "http://datafanthfuloss.oss-cn-shanghai.aliyuncs.com/cpsupload/pic/20190628142502016174.jpg"
        ]
    },
    {
        "id": "6394",
        "name": "怪物猎人 挂件 熟肉 CAPCOM",
        "englishName": "Monster Hunter Item Mascot Well-done Steak",
        "price": 50,
        "activityPrice": 50,
        "typeOne": 39,
        "typeTwo": 150,
        "themeOne": 45,
        "themeTwo": 239,
        "typeOneName": "饰品",
        "typeTwoName": "钥匙扣/挂件",
        "themeOneName": "Game",
        "themeTwoName": "Monster Hunter",
        "indexType": "0",
        "buyCount": 3,
        "isSellOut": 2,
        "imageList": "http://datafanthfuloss.oss-cn-shanghai.aliyuncs.com/cpsupload/pic/20190627155000199101.jpg",
        "isExtension": 2,
        "imageStrList": [
            "http://datafanthfuloss.oss-cn-shanghai.aliyuncs.com/cpsupload/pic/20190627155000199101.jpg"
        ]
    },
    {
        "id": "6393",
        "name": "怪物猎人 挂件 大爆弹桶 CAPCOM",
        "englishName": "Monster Hunter Item Mascot Large Barrel-Bomb",
        "price": 50,
        "activityPrice": 50,
        "typeOne": 39,
        "typeTwo": 150,
        "themeOne": 45,
        "themeTwo": 239,
        "typeOneName": "饰品",
        "typeTwoName": "钥匙扣/挂件",
        "themeOneName": "Game",
        "themeTwoName": "Monster Hunter",
        "indexType": "0",
        "buyCount": 4,
        "isSellOut": 2,
        "imageList": "http://datafanthfuloss.oss-cn-shanghai.aliyuncs.com/cpsupload/pic/20190627155000192010.jpg",
        "isExtension": 2,
        "imageStrList": [
            "http://datafanthfuloss.oss-cn-shanghai.aliyuncs.com/cpsupload/pic/20190627155000192010.jpg"
        ]
    },
    {
        "id": "6188",
        "name": "怪物猎人世界新大陆古龙调查团手提包",
        "englishName": "MHW the Research Commission's Shoulder Bag",
        "price": 49,
        "activityPrice": 49,
        "typeOne": 40,
        "typeTwo": 156,
        "themeOne": 45,
        "themeTwo": 239,
        "typeOneName": "箱包",
        "typeTwoName": "单肩包",
        "themeOneName": "Game",
        "themeTwoName": "Monster Hunter",
        "indexType": "8,3",
        "buyCount": 9,
        "isSellOut": 2,
        "imageList": "http://datafanthfuloss.oss-cn-shanghai.aliyuncs.com/cpsupload/pic/20190423145102912052.jpg,http://datafanthfuloss.oss-cn-shanghai.aliyuncs.com/cpsupload/pic/20190423145102946769.jpg,http://datafanthfuloss.oss-cn-shanghai.aliyuncs.com/cpsupload/pic/20190423145102965768.jpg,http://datafanthfuloss.oss-cn-shanghai.aliyuncs.com/cpsupload/pic/20190423145102963631.jpg",
        "isExtension": 2,
        "imageStrList": [
            "http://datafanthfuloss.oss-cn-shanghai.aliyuncs.com/cpsupload/pic/20190423145102912052.jpg",
            "http://datafanthfuloss.oss-cn-shanghai.aliyuncs.com/cpsupload/pic/20190423145102946769.jpg",
            "http://datafanthfuloss.oss-cn-shanghai.aliyuncs.com/cpsupload/pic/20190423145102965768.jpg",
            "http://datafanthfuloss.oss-cn-shanghai.aliyuncs.com/cpsupload/pic/20190423145102963631.jpg"
        ]
    },
    {
        "id": "6186",
        "name": "怪物猎人世界回复药笔记本",
        "englishName": "Monster Hunter World Potion Notebook",
        "price": 39,
        "activityPrice": 39,
        "typeOne": 41,
        "typeTwo": 159,
        "themeOne": 45,
        "themeTwo": 239,
        "typeOneName": "文具",
        "typeTwoName": "笔记本",
        "themeOneName": "Game",
        "themeTwoName": "Monster Hunter",
        "indexType": "8,3",
        "buyCount": 6,
        "isSellOut": 2,
        "imageList": "http://datafanthfuloss.oss-cn-shanghai.aliyuncs.com/cpsupload/pic/20190423132104597630.jpg,http://datafanthfuloss.oss-cn-shanghai.aliyuncs.com/cpsupload/pic/20190423132104547518.jpg,http://datafanthfuloss.oss-cn-shanghai.aliyuncs.com/cpsupload/pic/20190423132104516487.jpg",
        "isExtension": 2,
        "imageStrList": [
            "http://datafanthfuloss.oss-cn-shanghai.aliyuncs.com/cpsupload/pic/20190423132104597630.jpg",
            "http://datafanthfuloss.oss-cn-shanghai.aliyuncs.com/cpsupload/pic/20190423132104547518.jpg",
            "http://datafanthfuloss.oss-cn-shanghai.aliyuncs.com/cpsupload/pic/20190423132104516487.jpg"
        ]
    },
    {
        "id": "6185",
        "name": "怪物猎人世界熟肉笔记本",
        "englishName": "Monster Hunter World Roast Meat Notebook",
        "price": 39,
        "activityPrice": 39,
        "typeOne": 41,
        "typeTwo": 159,
        "themeOne": 45,
        "themeTwo": 239,
        "typeOneName": "文具",
        "typeTwoName": "笔记本",
        "themeOneName": "Game",
        "themeTwoName": "Monster Hunter",
        "indexType": "8,3",
        "buyCount": 2,
        "isSellOut": 2,
        "imageList": "http://datafanthfuloss.oss-cn-shanghai.aliyuncs.com/cpsupload/pic/20190423132104571126.jpg,http://datafanthfuloss.oss-cn-shanghai.aliyuncs.com/cpsupload/pic/20190423132104516487.jpg",
        "isExtension": 2,
        "imageStrList": [
            "http://datafanthfuloss.oss-cn-shanghai.aliyuncs.com/cpsupload/pic/20190423132104571126.jpg",
            "http://datafanthfuloss.oss-cn-shanghai.aliyuncs.com/cpsupload/pic/20190423132104516487.jpg"
        ]
    },
    {
        "id": "6165",
        "name": "怪物猎人世界刺绣徽章盲包第2弹（10个装）",
        "englishName": "MHW monster icon CAN-Badges collection(embroidery) - BOX",
        "price": 308,
        "activityPrice": 308,
        "typeOne": 39,
        "typeTwo": 149,
        "themeOne": 45,
        "themeTwo": 239,
        "typeOneName": "饰品",
        "typeTwoName": "徽章",
        "themeOneName": "Game",
        "themeTwoName": "Monster Hunter",
        "indexType": "3",
        "buyCount": 3,
        "isSellOut": 2,
        "imageList": "http://datafanthfuloss.oss-cn-shanghai.aliyuncs.com/cpsupload/pic/20190401182501866686.jpg,http://datafanthfuloss.oss-cn-shanghai.aliyuncs.com/cpsupload/pic/20190401182504247518.jpg,http://datafanthfuloss.oss-cn-shanghai.aliyuncs.com/cpsupload/pic/20190401182501828692.jpg,http://datafanthfuloss.oss-cn-shanghai.aliyuncs.com/cpsupload/pic/20190401182501811951.jpg,http://datafanthfuloss.oss-cn-shanghai.aliyuncs.com/cpsupload/pic/20190401182501886124.jpg,http://datafanthfuloss.oss-cn-shanghai.aliyuncs.com/cpsupload/pic/20190401182501815436.jpg,http://datafanthfuloss.oss-cn-shanghai.aliyuncs.com/cpsupload/pic/20190401182501823378.jpg,http://datafanthfuloss.oss-cn-shanghai.aliyuncs.com/cpsupload/pic/20190401182501850651.jpg",
        "isExtension": 2,
        "imageStrList": [
            "http://datafanthfuloss.oss-cn-shanghai.aliyuncs.com/cpsupload/pic/20190401182501866686.jpg",
            "http://datafanthfuloss.oss-cn-shanghai.aliyuncs.com/cpsupload/pic/20190401182504247518.jpg",
            "http://datafanthfuloss.oss-cn-shanghai.aliyuncs.com/cpsupload/pic/20190401182501828692.jpg",
            "http://datafanthfuloss.oss-cn-shanghai.aliyuncs.com/cpsupload/pic/20190401182501811951.jpg",
            "http://datafanthfuloss.oss-cn-shanghai.aliyuncs.com/cpsupload/pic/20190401182501886124.jpg",
            "http://datafanthfuloss.oss-cn-shanghai.aliyuncs.com/cpsupload/pic/20190401182501815436.jpg",
            "http://datafanthfuloss.oss-cn-shanghai.aliyuncs.com/cpsupload/pic/20190401182501823378.jpg",
            "http://datafanthfuloss.oss-cn-shanghai.aliyuncs.com/cpsupload/pic/20190401182501850651.jpg"
        ]
    },
    {
        "id": "6164",
        "name": "怪物猎人世界刺绣徽章盲包第2弹（随机一款）CAPCOM",
        "englishName": "MHW monster icon CAN-Badges collection(embroidery)",
        "price": 35,
        "activityPrice": 35,
        "typeOne": 39,
        "typeTwo": 149,
        "themeOne": 45,
        "themeTwo": 239,
        "typeOneName": "饰品",
        "typeTwoName": "徽章",
        "themeOneName": "Game",
        "themeTwoName": "Monster Hunter",
        "indexType": "0",
        "buyCount": 9,
        "isSellOut": 2,
        "imageList": "http://datafanthfuloss.oss-cn-shanghai.aliyuncs.com/cpsupload/pic/20190401182501866686.jpg,http://datafanthfuloss.oss-cn-shanghai.aliyuncs.com/cpsupload/pic/20190401182504247518.jpg,http://datafanthfuloss.oss-cn-shanghai.aliyuncs.com/cpsupload/pic/20190401182501811951.jpg,http://datafanthfuloss.oss-cn-shanghai.aliyuncs.com/cpsupload/pic/20190401182501828692.jpg,http://datafanthfuloss.oss-cn-shanghai.aliyuncs.com/cpsupload/pic/20190401182501886124.jpg,http://datafanthfuloss.oss-cn-shanghai.aliyuncs.com/cpsupload/pic/20190401182501815436.jpg,http://datafanthfuloss.oss-cn-shanghai.aliyuncs.com/cpsupload/pic/20190401182501823378.jpg,http://datafanthfuloss.oss-cn-shanghai.aliyuncs.com/cpsupload/pic/20190401182501850651.jpg",
        "isExtension": 2,
        "imageStrList": [
            "http://datafanthfuloss.oss-cn-shanghai.aliyuncs.com/cpsupload/pic/20190401182501866686.jpg",
            "http://datafanthfuloss.oss-cn-shanghai.aliyuncs.com/cpsupload/pic/20190401182504247518.jpg",
            "http://datafanthfuloss.oss-cn-shanghai.aliyuncs.com/cpsupload/pic/20190401182501811951.jpg",
            "http://datafanthfuloss.oss-cn-shanghai.aliyuncs.com/cpsupload/pic/20190401182501828692.jpg",
            "http://datafanthfuloss.oss-cn-shanghai.aliyuncs.com/cpsupload/pic/20190401182501886124.jpg",
            "http://datafanthfuloss.oss-cn-shanghai.aliyuncs.com/cpsupload/pic/20190401182501815436.jpg",
            "http://datafanthfuloss.oss-cn-shanghai.aliyuncs.com/cpsupload/pic/20190401182501823378.jpg",
            "http://datafanthfuloss.oss-cn-shanghai.aliyuncs.com/cpsupload/pic/20190401182501850651.jpg"
        ]
    }
]